<?xml version="1.0" encoding="utf-8"?>
<!--Detailed report on module Job-->
<CCCC_Project>
<module_summary>
<lines_of_code value="160" level="0" />
<lines_of_code_per_member_function value="******" level="0" />
<McCabes_cyclomatic_complexity value="26" level="0" />
<McCabes_cyclomatic_complexity_per_member_function value="******" level="2" />
<lines_of_code value="20" level="0" />
<lines_of_code_per_member_function value="********" level="2" />
<lines_of_code_per_line_of_comment value="8.000" level="1" />
<McCabes_cyclomatic_complexity_per_line_of_comment value="1.300" level="0" />
<weighted_methods_per_class_unity value="13" level="0" />
<weighted_methods_per_class_visibility value="10" level="0" />
<depth_of_inheritance_tree value="0" level="0" />
<number_of_children value="0" level="0" />
<coupling_between_objects value="7" level="0" />
<IF4 value="100" level="0" />
<IF4_per_member_function value="********" level="2" />
<IF4_visible value="64" level="1" />
<IF4_visible_per_member_function value="********" level="2" />
<IF4_concrete value="0" level="0" />
<IF4_concrete_per_member_function value="********" level="0" />
</module_summary>
<module_detail>
<description>declaration</description>
<source_reference file="Global.h" line="18" />
<lines_of_code value="1" level="0" />
<McCabes_cyclomatic_complexity value="0" level="0" />
<lines_of_comment value="0" level="0" />
<lines_of_code_per_line_of_comment value="------" level="0" />
<McCabes_cyclomatic_complexity_per_line_of_comment value="------" level="0" />
<description>definition</description>
<source_reference file="Job.h" line="13" />
<lines_of_code value="11" level="0" />
<McCabes_cyclomatic_complexity value="0" level="0" />
<lines_of_comment value="0" level="0" />
<lines_of_code_per_line_of_comment value="------" level="0" />
<McCabes_cyclomatic_complexity_per_line_of_comment value="------" level="0" />
<description>declaration</description>
<source_reference file="Manager.h" line="14" />
<lines_of_code value="1" level="0" />
<McCabes_cyclomatic_complexity value="0" level="0" />
<lines_of_comment value="1" level="0" />
<lines_of_code_per_line_of_comment value="------" level="0" />
<McCabes_cyclomatic_complexity_per_line_of_comment value="------" level="0" />
</module_detail>
<procedural_detail>
<member_function>
<name>Complete(bool)</name>
<extent>
<description>definition</description>
<source_reference file="Job.cpp" line="61" />
</extent>
<extent>
<description>declaration</description>
<source_reference file="Job.h" line="36" />
</extent>
<lines_of_code value="7" level="0" />
<McCabes_cyclomatic_complexity value="1" level="0" />
<lines_of_comment value="0" level="0" />
<lines_of_code_per_line_of_comment value="------" level="0" />
<McCabes_cyclomatic_complexity_per_line_of_comment value="------" level="0" />
</member_function>
<member_function>
<name>Job(int,Manager *,vector)</name>
<extent>
<description>definition</description>
<source_reference file="Job.cpp" line="9" />
</extent>
<extent>
<description>declaration</description>
<source_reference file="Job.h" line="23" />
</extent>
<lines_of_code value="12" level="0" />
<McCabes_cyclomatic_complexity value="1" level="0" />
<lines_of_comment value="6" level="0" />
<lines_of_code_per_line_of_comment value="------" level="0" />
<McCabes_cyclomatic_complexity_per_line_of_comment value="------" level="0" />
</member_function>
<member_function>
<name>Job(int,int,Manager *,vector,int,int,int,int,int)</name>
<extent>
<description>definition</description>
<source_reference file="Job.cpp" line="22" />
</extent>
<extent>
<description>declaration</description>
<source_reference file="Job.h" line="24" />
</extent>
<lines_of_code value="13" level="0" />
<McCabes_cyclomatic_complexity value="2" level="0" />
<lines_of_comment value="3" level="0" />
<lines_of_code_per_line_of_comment value="------" level="0" />
<McCabes_cyclomatic_complexity_per_line_of_comment value="------" level="0" />
</member_function>
<member_function>
<name>getComID()</name>
<extent>
<description>definition</description>
<source_reference file="Job.cpp" line="39" />
</extent>
<extent>
<description>declaration</description>
<source_reference file="Job.h" line="30" />
</extent>
<lines_of_code value="2" level="0" />
<McCabes_cyclomatic_complexity value="1" level="0" />
<lines_of_comment value="0" level="0" />
<lines_of_code_per_line_of_comment value="------" level="0" />
<McCabes_cyclomatic_complexity_per_line_of_comment value="------" level="0" />
</member_function>
<member_function>
<name>getID()</name>
<extent>
<description>definition</description>
<source_reference file="Job.cpp" line="37" />
</extent>
<extent>
<description>declaration</description>
<source_reference file="Job.h" line="28" />
</extent>
<lines_of_code value="2" level="0" />
<McCabes_cyclomatic_complexity value="1" level="0" />
<lines_of_comment value="0" level="0" />
<lines_of_code_per_line_of_comment value="------" level="0" />
<McCabes_cyclomatic_complexity_per_line_of_comment value="------" level="0" />
</member_function>
<member_function>
<name>getUniqueID()</name>
<extent>
<description>definition</description>
<source_reference file="Job.cpp" line="41" />
</extent>
<extent>
<description>declaration</description>
<source_reference file="Job.h" line="43" />
</extent>
<lines_of_code value="16" level="0" />
<McCabes_cyclomatic_complexity value="3" level="0" />
<lines_of_comment value="1" level="0" />
<lines_of_code_per_line_of_comment value="------" level="0" />
<McCabes_cyclomatic_complexity_per_line_of_comment value="------" level="0" />
</member_function>
<member_function>
<name>isCompleted()</name>
<extent>
<description>definition</description>
<source_reference file="Job.cpp" line="57" />
</extent>
<extent>
<description>declaration</description>
<source_reference file="Job.h" line="32" />
</extent>
<lines_of_code value="2" level="0" />
<McCabes_cyclomatic_complexity value="1" level="0" />
<lines_of_comment value="0" level="0" />
<lines_of_code_per_line_of_comment value="------" level="0" />
<McCabes_cyclomatic_complexity_per_line_of_comment value="------" level="0" />
</member_function>
<member_function>
<name>isHighlight()</name>
<extent>
<description>definition</description>
<source_reference file="Job.cpp" line="59" />
</extent>
<extent>
<description>declaration</description>
<source_reference file="Job.h" line="34" />
</extent>
<lines_of_code value="2" level="0" />
<McCabes_cyclomatic_complexity value="1" level="0" />
<lines_of_comment value="0" level="0" />
<lines_of_code_per_line_of_comment value="------" level="0" />
<McCabes_cyclomatic_complexity_per_line_of_comment value="------" level="0" />
</member_function>
<member_function>
<name>printDetail()</name>
<extent>
<description>definition</description>
<source_reference file="Job.cpp" line="68" />
</extent>
<extent>
<description>declaration</description>
<source_reference file="Job.h" line="38" />
</extent>
<lines_of_code value="9" level="0" />
<McCabes_cyclomatic_complexity value="2" level="0" />
<lines_of_comment value="0" level="0" />
<lines_of_code_per_line_of_comment value="------" level="0" />
<McCabes_cyclomatic_complexity_per_line_of_comment value="------" level="0" />
</member_function>
<member_function>
<name>read()</name>
<extent>
<description>definition</description>
<source_reference file="Job.cpp" line="35" />
</extent>
<extent>
<description>declaration</description>
<source_reference file="Job.h" line="26" />
</extent>
<lines_of_code value="2" level="0" />
<McCabes_cyclomatic_complexity value="0" level="0" />
<lines_of_comment value="0" level="0" />
<lines_of_code_per_line_of_comment value="------" level="0" />
<McCabes_cyclomatic_complexity_per_line_of_comment value="------" level="0" />
</member_function>
<member_function>
<name>removeEmp(Employee *)</name>
<extent>
<description>definition</description>
<source_reference file="Job.cpp" line="77" />
</extent>
<extent>
<description>declaration</description>
<source_reference file="Job.h" line="40" />
</extent>
<lines_of_code value="5" level="0" />
<McCabes_cyclomatic_complexity value="0" level="0" />
<lines_of_comment value="0" level="0" />
<lines_of_code_per_line_of_comment value="------" level="0" />
<McCabes_cyclomatic_complexity_per_line_of_comment value="------" level="0" />
</member_function>
<member_function>
<name>updateFile(int)</name>
<extent>
<description>definition</description>
<source_reference file="Job.cpp" line="97" />
</extent>
<extent>
<description>declaration</description>
<source_reference file="Job.h" line="44" />
</extent>
<lines_of_code value="60" level="1" />
<McCabes_cyclomatic_complexity value="10" level="0" />
<lines_of_comment value="9" level="0" />
<lines_of_code_per_line_of_comment value="6.667" level="0" />
<McCabes_cyclomatic_complexity_per_line_of_comment value="1.111" level="0" />
</member_function>
<member_function>
<name>writeToFile()</name>
<extent>
<description>definition</description>
<source_reference file="Job.cpp" line="82" />
</extent>
<extent>
<description>declaration</description>
<source_reference file="Job.h" line="42" />
</extent>
<lines_of_code value="15" level="0" />
<McCabes_cyclomatic_complexity value="3" level="0" />
<lines_of_comment value="0" level="0" />
<lines_of_code_per_line_of_comment value="------" level="0" />
<McCabes_cyclomatic_complexity_per_line_of_comment value="------" level="0" />
</member_function>
</procedural_detail>
<structural_detail>
<module>
<name>Job</name>
<client_module>
<name>Employee</name>
<visible>true</visible>
<concrete>false</concrete>
<extent>
<description>pass by reference</description>
<source_reference file="Employee.cpp" line="34" />
</extent>
<extent>
<description>pass by reference</description>
<source_reference file="Employee.h" line="33" />
</extent>
<name>Manager</name>
<visible>true</visible>
<concrete>false</concrete>
<extent>
<description>pass by reference</description>
<source_reference file="Manager.cpp" line="30" />
</extent>
<extent>
<description>pass by reference</description>
<source_reference file="Manager.h" line="27" />
</extent>
</client_module>
<supplier_module>
<name>Date</name>
<visible>false</visible>
<concrete>false</concrete>
<extent>
<description>has by reference</description>
<source_reference file="Job.h" line="16" />
</extent>
<name>Employee</name>
<visible>true</visible>
<concrete>false</concrete>
<extent>
<description>pass by reference</description>
<source_reference file="Job.cpp" line="77" />
</extent>
<extent>
<description>pass by reference</description>
<source_reference file="Job.h" line="40" />
</extent>
<name>Manager</name>
<visible>true</visible>
<concrete>false</concrete>
<extent>
<description>pass by reference</description>
<source_reference file="Job.cpp" line="9" />
</extent>
<extent>
<description>pass by reference</description>
<source_reference file="Job.cpp" line="22" />
</extent>
<extent>
<description>has by reference</description>
<source_reference file="Job.h" line="17" />
</extent>
<extent>
<description>pass by reference</description>
<source_reference file="Job.h" line="23" />
</extent>
<extent>
<description>pass by reference</description>
<source_reference file="Job.h" line="24" />
</extent>
<name>bool</name>
<visible>true</visible>
<concrete>true</concrete>
<extent>
<description>pass by value</description>
<source_reference file="Job.cpp" line="61" />
</extent>
<extent>
<description>has by value</description>
<source_reference file="Job.h" line="19" />
</extent>
<extent>
<description>has by value</description>
<source_reference file="Job.h" line="20" />
</extent>
<extent>
<description>pass by value</description>
<source_reference file="Job.h" line="36" />
</extent>
<name>vector</name>
<visible>true</visible>
<concrete>true</concrete>
<extent>
<description>pass by value</description>
<source_reference file="Job.cpp" line="9" />
</extent>
<extent>
<description>pass by value</description>
<source_reference file="Job.cpp" line="22" />
</extent>
<extent>
<description>has by value</description>
<source_reference file="Job.h" line="18" />
</extent>
<extent>
<description>pass by value</description>
<source_reference file="Job.h" line="23" />
</extent>
<extent>
<description>pass by value</description>
<source_reference file="Job.h" line="24" />
</extent>
</supplier_module>
</module>
</structural_detail>
</CCCC_Project>
